synthval/__init__.py
synthval/configs.py
synthval/features_extraction.py
synthval/metrics.py
synthval/utilities.py
synthval-0.2.4a0.dist-info/licenses/LICENSE
synthval-0.2.4a0.dist-info/METADATA
synthval-0.2.4a0.dist-info/WHEEL
synthval-0.2.4a0.dist-info/top_level.txt
synthval-0.2.4a0.dist-info/RECORD
