Metadata-Version: 2.4
Name: SynthVal
Version: 0.2.4a0
Summary: Package designed to validate the quality of synthetically generated data, with a focus on medical images like chest x-rays and mammographies, by providing tools for feature extraction and similarity metric calculations to compare original and synthetic datasets.
Home-page: https://github.com/AIMet-Lab/SynthVal
Author: Dario Guidotti, Laura Pandolfo, Luca Pulina
Author-email: dguidotti@uniss.it, lpandolfo@uniss.it, lpulina@uniss.it
License: GNU General Public License with Commons Clause License Condition v1.0
Classifier: Programming Language :: Python :: 3.10
Classifier: Development Status :: 2 - Pre-Alpha
Classifier: Topic :: Scientific/Engineering :: Artificial Intelligence
Classifier: Operating System :: OS Independent
Requires-Python: >=3.10
License-File: LICENSE
Requires-Dist: pillow
Requires-Dist: pydicom
Requires-Dist: numpy
Requires-Dist: pandas
Requires-Dist: timm
Requires-Dist: torch
Requires-Dist: transformers
Requires-Dist: scipy
Requires-Dist: dcor
Requires-Dist: pynever
Requires-Dist: scikit-learn
Dynamic: author
Dynamic: author-email
Dynamic: classifier
Dynamic: description
Dynamic: home-page
Dynamic: license
Dynamic: license-file
Dynamic: requires-dist
Dynamic: requires-python
Dynamic: summary
